safellmkit/__init__.py
safellmkit/cli.py
safellmkit/engine.py
safellmkit/models.py
safellmkit/ml/__init__.py
safellmkit/ml/onnx_classifier.py
safellmkit/ml/tokenizer.py
safellmkit/policies/relaxed.json
safellmkit/policies/strict.json
safellmkit/rules/__init__.py
safellmkit/rules/base.py
safellmkit/rules/pii.py
safellmkit/rules/prompt_injection.py
safellmkit/rules/signal_jailbreak.py
safellmkit/rules/toxicity.py
safellmkit-0.1.0.dist-info/METADATA
safellmkit-0.1.0.dist-info/WHEEL
safellmkit-0.1.0.dist-info/entry_points.txt
safellmkit-0.1.0.dist-info/top_level.txt
safellmkit-0.1.0.dist-info/RECORD
