Metadata-Version: 2.4
Name: safellmkit
Version: 0.1.0
Summary: Universal Guardrails SDK for Large Language Models
Author-email: SafeLLMKit Team <maintainer@safellmkit.org>
Classifier: Programming Language :: Python :: 3
Classifier: License :: OSI Approved :: MIT License
Classifier: Operating System :: OS Independent
Classifier: Topic :: Security
Classifier: Topic :: Scientific/Engineering :: Artificial Intelligence
Requires-Python: >=3.9
Requires-Dist: pydantic>=2.0.0
Provides-Extra: onnx
Requires-Dist: onnxruntime>=1.16.0; extra == "onnx"
Requires-Dist: numpy>=1.20.0; extra == "onnx"
Provides-Extra: dev
Requires-Dist: pytest>=7.0.0; extra == "dev"
Requires-Dist: build; extra == "dev"
Requires-Dist: twine; extra == "dev"
